{
  "main": {
    "id": "3da0ad4e5263b523",
    "type": "split",
    "children": [
      {
        "id": "2019c64609d9cc3c",
        "type": "tabs",
        "children": [
          {
            "id": "7f5a705dfeebc5a1",
            "type": "leaf",
            "state": {
              "type": "markdown",
              "state": {
                "file": "OverTheWire Bandit.md",
                "mode": "source",
                "source": false
              },
              "icon": "lucide-file",
              "title": "OverTheWire Bandit"
            }
          }
        ]
      }
    ],
    "direction": "vertical"
  },
  "left": {
    "id": "905aea5d35b43d50",
    "type": "split",
    "children": [
      {
        "id": "a003bc2bb1c0d2f8",
        "type": "tabs",
        "children": [
          {
            "id": "10475973ee217306",
            "type": "leaf",
            "state": {
              "type": "file-explorer",
              "state": {
                "sortOrder": "alphabetical",
                "autoReveal": false
              },
              "icon": "lucide-folder-closed",
              "title": "Files"
            }
          },
          {
            "id": "67e54803c30bf023",
            "type": "leaf",
            "state": {
              "type": "search",
              "state": {
                "query": "tag:#matlab",
                "matchingCase": false,
                "explainSearch": false,
                "collapseAll": false,
                "extraContext": false,
                "sortOrder": "alphabetical"
              },
              "icon": "lucide-search",
              "title": "Search"
            }
          },
          {
            "id": "816912c0d027ce63",
            "type": "leaf",
            "state": {
              "type": "bookmarks",
              "state": {},
              "icon": "lucide-bookmark",
              "title": "Bookmarks"
            }
          }
        ]
      }
    ],
    "direction": "horizontal",
    "width": 300
  },
  "right": {
    "id": "babe6ea245ea31d1",
    "type": "split",
    "children": [
      {
        "id": "f23f757451db3cb5",
        "type": "tabs",
        "children": [
          {
            "id": "5df888d785ed6dac",
            "type": "leaf",
            "state": {
              "type": "backlink",
              "state": {
                "collapseAll": false,
                "extraContext": false,
                "sortOrder": "alphabetical",
                "showSearch": false,
                "searchQuery": "",
                "backlinkCollapsed": false,
                "unlinkedCollapsed": false
              },
              "icon": "links-coming-in",
              "title": "Backlinks"
            }
          },
          {
            "id": "1bc15ff44867deea",
            "type": "leaf",
            "state": {
              "type": "outgoing-link",
              "state": {
                "linksCollapsed": false,
                "unlinkedCollapsed": true
              },
              "icon": "links-going-out",
              "title": "Outgoing links"
            }
          },
          {
            "id": "b699a68cba2ea125",
            "type": "leaf",
            "state": {
              "type": "tag",
              "state": {
                "sortOrder": "frequency",
                "useHierarchy": false
              },
              "icon": "lucide-tags",
              "title": "Tags"
            }
          },
          {
            "id": "bd1cc8a700de7b59",
            "type": "leaf",
            "state": {
              "type": "outline",
              "state": {},
              "icon": "lucide-list",
              "title": "Outline"
            }
          }
        ],
        "currentTab": 1
      }
    ],
    "direction": "horizontal",
    "width": 300,
    "collapsed": true
  },
  "left-ribbon": {
    "hiddenItems": {
      "bases:Create new base": false,
      "switcher:Open quick switcher": false,
      "graph:Open graph view": false,
      "canvas:Create new canvas": false,
      "daily-notes:Open today's daily note": false,
      "templates:Insert template": false,
      "command-palette:Open command palette": false
    }
  },
  "active": "7f5a705dfeebc5a1",
  "lastOpenFiles": [
    "OverTheWire Bandit.md",
    "NC Linux.md",
    "AI Agents.md",
    "Artificial Intelligence.md",
    "freecodecamp CSS.md",
    "freecodecamp HTML.md",
    "Git and Github.md",
    "Markdown Basics.md",
    "MATLAB Onramp.md",
    "NC Bash Scripting.md",
    "README.md",
    "ROS & Gazebo.md",
    "Simulink Onramp.md",
    "Stateflow Onramp.md",
    "Statistics Onramp.md",
    "attachments/MATLAB/Stateflow Action.png",
    "attachments/MATLAB/Simulink/Pasted image 20250718130958.png",
    "attachments/MATLAB/Simulink/Pasted image 20250718130903.png",
    "attachments/MATLAB/Simulink/Pasted image 20250718130756.png",
    "attachments/MATLAB/Simulink/Pasted image 20250718130847.png",
    "attachments/MATLAB/Simulink/Pasted image 20250718130736.png",
    "attachments/MATLAB/Simulink/Pasted image 20250718130706.png",
    "attachments/MATLAB/Simulink/Pasted image 20250718130652.png",
    "attachments/MATLAB/Simulink/Pasted image 20250718130507.png",
    "attachments/MATLAB/Simulink/Pasted image 20250718130420.png",
    "attachments/MATLAB/Simulink",
    "attachments/Simulink",
    "attachments/New folder",
    "attachments/ROS&Gazebo/README(RoseCityRobotics_Github_robotics-resources).md",
    "attachments/ROS&Gazebo/Unconfirmed 758495.crdownload",
    "attachments/ROS&Gazebo/Introduction to ROS.pdf",
    "attachments/ROS&Gazebo/Introduction to ROS.pdf.crdownload",
    "attachments/ROS&Gazebo",
    "attachments/MATLAB/Statistics Onramp Quick Reference.pdf",
    "autocommit.sh",
    "attachments/MATLAB/matlab-basic-functions-reference.pdf",
    "attachments/markdown-cheat-sheet.md",
    "Untitled.canvas",
    "Guvi Python.md",
    "Responsive Web Design freecodecamp.md",
    "Welcome.md"
  ]
}